yta_ai_blip/__init__.py
yta_ai_blip-0.0.2.dist-info/LICENSE
yta_ai_blip-0.0.2.dist-info/METADATA
yta_ai_blip-0.0.2.dist-info/WHEEL
yta_ai_blip-0.0.2.dist-info/RECORD
