Metadata-Version: 2.3
Name: yta-ai-blip
Version: 0.0.2
Summary: Youtube Autonomous AI Blip Module.
Author: danialcala94
Author-email: danielalcalavalera@gmail.com
Requires-Python: ==3.9
Classifier: Programming Language :: Python :: 3
Classifier: Programming Language :: Python :: 3.9
Requires-Dist: transformers (>=4.0.0,<5.0.0)
Requires-Dist: yta_image (>=0.0.1,<1.0.0)
